tcal/__init__.py
tcal/tcal.py
yu_tcal-3.1.0.dist-info/METADATA
yu_tcal-3.1.0.dist-info/WHEEL
yu_tcal-3.1.0.dist-info/entry_points.txt
yu_tcal-3.1.0.dist-info/licenses/LICENSE
yu_tcal-3.1.0.dist-info/RECORD
