Metadata-Version: 2.4
Name: yu-tcal
Version: 3.1.0
Summary: Add your description here
Author: Koki Ozawa
Author-email: Hiroyuki Matsui <h-matsui@yz.yamagata-u.ac.jp>
License: MIT License
License-File: LICENSE
Keywords: interatomic transfer integral,organic semiconductor,transfer integral
Classifier: Development Status :: 5 - Production/Stable
Classifier: Intended Audience :: Education
Classifier: Intended Audience :: Science/Research
Classifier: License :: OSI Approved :: MIT License
Classifier: Programming Language :: Python :: 3.9
Classifier: Programming Language :: Python :: 3.10
Classifier: Programming Language :: Python :: 3.11
Classifier: Programming Language :: Python :: 3.12
Classifier: Programming Language :: Python :: 3.13
Classifier: Topic :: Scientific/Engineering
Classifier: Topic :: Scientific/Engineering :: Chemistry
Classifier: Topic :: Scientific/Engineering :: Physics
Requires-Python: >=3.9
Requires-Dist: numpy>=2.0.2
